{
  "project": [
    {
      "name": "SportMoon",
      "type": "Fullstack",
      "url_code": "https://github.com/abram001X/SportsMoon",
      "url_page": "https://frontend-sportsmoon.onrender.com",
      "img": "https://github.com/abram001X/My-Portfolio/blob/main/My-Portfolio/img/Opera%20Instant%C3%A1nea_2024-07-24_150415_localhost.png?raw=true",
      "description": "SportMoon es una página de fútbol, dedicado exclusivamente a todo lo relacionado con este deporte.",
      "tecnologia": ["React", "NodeJs", "ExpressJs", "Sql"]
    },
    {
      "name": "ConvertMoonJs",
      "type": "Fullstack",
      "img": "https://github.com/abram001X/My-Portfolio/blob/main/My-Portfolio/img/convertmoon-link.png?raw=true",
      "url_code": "https://github.com/abram001X/convertMoonJs",
      "url_page": "https://convert-moon.netlify.app",
      "description": "ConvertMoon es una página web que te permite convertir videos de YouTube para que puedas descargarlos.",
      "tecnologia": ["React", "HTML", "Css"]
    },
    {
      "name": "E-commerce-fake",
      "img": "https://github.com/abram001X/My-Portfolio/blob/main/My-Portfolio/img/e-commerce.png?raw=true",
      "type": "FullStack",
      "url_code": "https://github.com/abram001X/E-commerce",
      "url_page": "https://ecommercefake.netlify.app/",
      "description": "¡En E-commerce-fake puedes ver los productos publicados, iniciar sesión con tu cuenta y publicar tus productos!",
      "tecnologia": ["React", "NodeJs", "Sql", "JavaScript", "git"]
    }
  ]
}
